{"nodes": [{"id": "o_hr_services_reporting_service_app_template_py", "label": "template.py", "file_type": "code", "source_file": "O:\\Hr\\services\\reporting-service\\app\\template.py", "source_location": "L1"}, {"id": "app_template_rows", "label": "_rows()", "file_type": "code", "source_file": "O:\\Hr\\services\\reporting-service\\app\\template.py", "source_location": "L6"}, {"id": "str", "label": "str", "file_type": "code", "source_file": "O:\\Hr\\services\\reporting-service\\app\\template.py", "source_location": "L6"}, {"id": "app_template_render_payslip_html", "label": "render_payslip_html()", "file_type": "code", "source_file": "O:\\Hr\\services\\reporting-service\\app\\template.py", "source_location": "L13"}, {"id": "app_template_rationale_1", "label": "Payslip HTML rendering from a payroll-result breakdown_json.", "file_type": "rationale", "source_file": "O:\\Hr\\services\\reporting-service\\app\\template.py", "source_location": "L1"}], "edges": [{"source": "o_hr_services_reporting_service_app_template_py", "target": "app_template_rows", "relation": "contains", "confidence": "EXTRACTED", "source_file": "O:\\Hr\\services\\reporting-service\\app\\template.py", "source_location": "L6", "weight": 1.0}, {"source": "app_template_rows", "target": "str", "relation": "references", "context": "return_type", "confidence": "EXTRACTED", "source_file": "O:\\Hr\\services\\reporting-service\\app\\template.py", "source_location": "L6", "weight": 1.0}, {"source": "o_hr_services_reporting_service_app_template_py", "target": "app_template_render_payslip_html", "relation": "contains", "confidence": "EXTRACTED", "source_file": "O:\\Hr\\services\\reporting-service\\app\\template.py", "source_location": "L13", "weight": 1.0}, {"source": "app_template_render_payslip_html", "target": "str", "relation": "references", "context": "parameter_type", "confidence": "EXTRACTED", "source_file": "O:\\Hr\\services\\reporting-service\\app\\template.py", "source_location": "L13", "weight": 1.0}, {"source": "app_template_render_payslip_html", "target": "str", "relation": "references", "context": "return_type", "confidence": "EXTRACTED", "source_file": "O:\\Hr\\services\\reporting-service\\app\\template.py", "source_location": "L13", "weight": 1.0}, {"source": "app_template_render_payslip_html", "target": "app_template_rows", "relation": "calls", "context": "call", "confidence": "EXTRACTED", "source_file": "O:\\Hr\\services\\reporting-service\\app\\template.py", "source_location": "L65", "weight": 1.0}, {"source": "app_template_rationale_1", "target": "o_hr_services_reporting_service_app_template_py", "relation": "rationale_for", "confidence": "EXTRACTED", "source_file": "O:\\Hr\\services\\reporting-service\\app\\template.py", "source_location": "L1", "weight": 1.0}], "raw_calls": [{"caller_nid": "app_template_rows", "callee": "join", "is_member_call": true, "source_file": "O:\\Hr\\services\\reporting-service\\app\\template.py", "source_location": "L7"}, {"caller_nid": "app_template_rows", "callee": "items", "is_member_call": true, "source_file": "O:\\Hr\\services\\reporting-service\\app\\template.py", "source_location": "L9"}, {"caller_nid": "app_template_render_payslip_html", "callee": "get", "is_member_call": true, "source_file": "O:\\Hr\\services\\reporting-service\\app\\template.py", "source_location": "L14"}, {"caller_nid": "app_template_render_payslip_html", "callee": "get", "is_member_call": true, "source_file": "O:\\Hr\\services\\reporting-service\\app\\template.py", "source_location": "L15"}, {"caller_nid": "app_template_render_payslip_html", "callee": "get", "is_member_call": true, "source_file": "O:\\Hr\\services\\reporting-service\\app\\template.py", "source_location": "L16"}, {"caller_nid": "app_template_render_payslip_html", "callee": "get", "is_member_call": true, "source_file": "O:\\Hr\\services\\reporting-service\\app\\template.py", "source_location": "L17"}, {"caller_nid": "app_template_render_payslip_html", "callee": "get", "is_member_call": true, "source_file": "O:\\Hr\\services\\reporting-service\\app\\template.py", "source_location": "L20"}, {"caller_nid": "app_template_render_payslip_html", "callee": "get", "is_member_call": true, "source_file": "O:\\Hr\\services\\reporting-service\\app\\template.py", "source_location": "L21"}, {"caller_nid": "app_template_render_payslip_html", "callee": "get", "is_member_call": true, "source_file": "O:\\Hr\\services\\reporting-service\\app\\template.py", "source_location": "L22"}, {"caller_nid": "app_template_render_payslip_html", "callee": "get", "is_member_call": true, "source_file": "O:\\Hr\\services\\reporting-service\\app\\template.py", "source_location": "L23"}, {"caller_nid": "app_template_render_payslip_html", "callee": "get", "is_member_call": true, "source_file": "O:\\Hr\\services\\reporting-service\\app\\template.py", "source_location": "L26"}, {"caller_nid": "app_template_render_payslip_html", "callee": "get", "is_member_call": true, "source_file": "O:\\Hr\\services\\reporting-service\\app\\template.py", "source_location": "L27"}, {"caller_nid": "app_template_render_payslip_html", "callee": "get", "is_member_call": true, "source_file": "O:\\Hr\\services\\reporting-service\\app\\template.py", "source_location": "L28"}, {"caller_nid": "app_template_render_payslip_html", "callee": "get", "is_member_call": true, "source_file": "O:\\Hr\\services\\reporting-service\\app\\template.py", "source_location": "L29"}, {"caller_nid": "app_template_render_payslip_html", "callee": "get", "is_member_call": true, "source_file": "O:\\Hr\\services\\reporting-service\\app\\template.py", "source_location": "L30"}, {"caller_nid": "app_template_render_payslip_html", "callee": "get", "is_member_call": true, "source_file": "O:\\Hr\\services\\reporting-service\\app\\template.py", "source_location": "L31"}, {"caller_nid": "app_template_render_payslip_html", "callee": "get", "is_member_call": true, "source_file": "O:\\Hr\\services\\reporting-service\\app\\template.py", "source_location": "L52"}, {"caller_nid": "app_template_render_payslip_html", "callee": "get", "is_member_call": true, "source_file": "O:\\Hr\\services\\reporting-service\\app\\template.py", "source_location": "L52"}, {"caller_nid": "app_template_render_payslip_html", "callee": "get", "is_member_call": true, "source_file": "O:\\Hr\\services\\reporting-service\\app\\template.py", "source_location": "L52"}, {"caller_nid": "app_template_render_payslip_html", "callee": "get", "is_member_call": true, "source_file": "O:\\Hr\\services\\reporting-service\\app\\template.py", "source_location": "L54"}, {"caller_nid": "app_template_render_payslip_html", "callee": "get", "is_member_call": true, "source_file": "O:\\Hr\\services\\reporting-service\\app\\template.py", "source_location": "L54"}, {"caller_nid": "app_template_render_payslip_html", "callee": "get", "is_member_call": true, "source_file": "O:\\Hr\\services\\reporting-service\\app\\template.py", "source_location": "L55"}, {"caller_nid": "app_template_render_payslip_html", "callee": "get", "is_member_call": true, "source_file": "O:\\Hr\\services\\reporting-service\\app\\template.py", "source_location": "L56"}, {"caller_nid": "app_template_render_payslip_html", "callee": "get", "is_member_call": true, "source_file": "O:\\Hr\\services\\reporting-service\\app\\template.py", "source_location": "L57"}, {"caller_nid": "app_template_render_payslip_html", "callee": "get", "is_member_call": true, "source_file": "O:\\Hr\\services\\reporting-service\\app\\template.py", "source_location": "L58"}, {"caller_nid": "app_template_render_payslip_html", "callee": "get", "is_member_call": true, "source_file": "O:\\Hr\\services\\reporting-service\\app\\template.py", "source_location": "L59"}, {"caller_nid": "app_template_render_payslip_html", "callee": "get", "is_member_call": true, "source_file": "O:\\Hr\\services\\reporting-service\\app\\template.py", "source_location": "L59"}, {"caller_nid": "app_template_render_payslip_html", "callee": "get", "is_member_call": true, "source_file": "O:\\Hr\\services\\reporting-service\\app\\template.py", "source_location": "L60"}]}